[
    {
      "name": "Photography Course",
      "img": "https://demo.nurcodes.com/E-LMS/php/img/course/r1.jpg",
      "desciption": "Grab fat our best photography course. You will learn full photography rules here with professional teacher",
      "price": "$150"
    },
    {
      "name": "Web Design Course",
      "img": "https://demo.nurcodes.com/E-LMS/php/img/course/r2.jpg",
      "desciption": "Grab fast our best web design course. You will learn full web design here with professional teacher",
      "price": "$200"
    },
    {
      "name": "UI/UX Design Course",
      "img": "https://demo.nurcodes.com/E-LMS/php/img/course/r3.jpg",
      "desciption": "Grab fat our best UI/UX design course. You will learn full  UI/UX design here with professional teacher",
      "price": "$100"
    },
    {
      "name": "React Course",
      "img": "https://reactjs.org/logo-og.png",
      "desciption": "Grab fast our React developer course. You will learn full react development here with professional teacher",
      "price": "$200"
    }
  ]